georgian_numbers/__init__.py
georgian_numbers/numbers_converter.py
georgian_numbers/utils/__init__.py
georgian_numbers/utils/utils.py
georgian_numbers-0.1.5.dist-info/LICENSE
georgian_numbers-0.1.5.dist-info/METADATA
georgian_numbers-0.1.5.dist-info/WHEEL
georgian_numbers-0.1.5.dist-info/top_level.txt
georgian_numbers-0.1.5.dist-info/RECORD
