Metadata-Version: 2.1
Name: georgian-numbers
Version: 0.1.5
Summary: It converts numbers in Georgian Language
Author: CCXLV
License: MIT
License-File: LICENSE
